Workbook

Sheet Clasificación fondos
A1: Nº | B1: Ticker / ISIN Bloomberg | C1: Nombre fondo | D1: Categoría principal | E1: Subcategoría | F1: Estilo / temática | G1: Región | H1: Divisa clase | I1: Uso docente | J1: Revisión | K1: Tiene histórico | L1: Primera fecha | M1: Última fecha | N1: Nº observaciones
A2: 1 | B2: IE00BYX5NX33 Equity | C2: FIDELITY-MSCI WLD IDX-PAEUR | D2: Renta Variable | E2: Global desarrollada | F2: Indexado / core | G2: Global | H2: EUR | I2: Core RV global | J2: Revisar con folleto/BD definitiva | K2: Sí | L2: 44316 | M2: 46142 | N2: 61
A3: 2 | B3: LU1347437789 Equity | C3: NSF-WEALTH DEFEN GL EQ-A EUR | D3: Renta Variable | E3: Global defensiva | F3: Defensivo / calidad | G3: Global | H3: EUR | I3: RV defensiva | J3: Revisar con folleto/BD definitiva | K3: Sí | L3: 44316 | M3: 46142 | N3: 61
A4: 3 | B4: LU1295551144 Equity | C4: CAPITAL GP NEW PERS-BEUR | D4: Renta Variable | E4: Global | F4: Growth / calidad | G4: Global | H4: EUR | I4: RV global activa | J4: Revisar con folleto/BD definitiva | K4: Sí | L4: 44316 | M4: 46142 | N4: 61
A5: 4 | B5: LU1076253134 Equity | C5: WELL GBL QTY GROWTH S EUR AC | D5: Renta Variable | E5: Global | F5: Quality growth | G5: Global | H5: EUR | I5: RV global activa | J5: Revisar con folleto/BD definitiva | K5: Sí | L5: 44316 | M5: 46142 | N5: 61
A6: 5 | B6: LU0203975437 Equity | C6: ROBECO BP GLBL PREM EQT-DEUR | D6: Renta Variable | E6: Global | F6: Value / premium equities | G6: Global | H6: EUR | I6: RV global value | J6: Revisar con folleto/BD definitiva | K6: Sí | L6: 44316 | M6: 46142 | N6: 61
A7: 6 | B7: ES0112611001 Equity | C7: AZVALOR INTERNACIONAL FI | D7: Renta Variable | E7: Global | F7: Value | G7: Global | H7: EUR | I7: RV global value | J7: Revisar con folleto/BD definitiva | K7: Sí | L7: 44316 | M7: 46142 | N7: 61
A8: 7 | B8: IE00BD0NCM55 Equity | C8: ISHR DEV WRLD IDX-D ACC EUR | D8: Renta Variable | E8: Global desarrollada | F8: Indexado / core | G8: Global | H8: EUR | I8: Core RV global | J8: Revisar con folleto/BD definitiva | K8: Sí | L8: 44316 | M8: 46142 | N8: 61
A9: 8 | B9: ES0110485010 Equity | C9: TRESSIS CARTERA ECO30 FI-R | D9: Renta Variable | E9: Global / temática | F9: Sostenibilidad / selección | G9: Global | H9: EUR | I9: RV temática/global | J9: Revisar con folleto/BD definitiva | K9: Sí | L9: 44316 | M9: 46142 | N9: 61
A10: 9 | B10: IE00BDRK7L36 Equity | C10: ISHARE-EU-IF-EUR-DA | D10: Renta Fija | E10: Gobierno euro inflación | F10: Inflation-linked | G10: Eurozona | H10: EUR | I10: RF defensiva inflación | J10: Revisar con folleto/BD definitiva | K10: Sí | L10: 44316 | M10: 46142 | N10: 61
A11: 10 | B11: LU0515381530 Equity | C11: CT LUX EUROPEAN G&I AINCEUR | D11: Renta Variable | E11: Europa | F11: Growth & income | G11: Europa | H11: EUR | I11: RV Europa | J11: Revisar con folleto/BD definitiva | K11: Sí | L11: 44316 | M11: 46142 | N11: 61
A12: 11 | B12: IE00B8BPMF80 Equity | C12: WELL STRAT EUR EQ-D EUR AC | D12: Renta Variable | E12: Europa | F12: Core / estratégica | G12: Europa | H12: EUR | I12: RV Europa | J12: Revisar con folleto/BD definitiva | K12: Sí | L12: 44316 | M12: 46142 | N12: 61
A13: 12 | B13: LU0125951151 Equity | C13: MFS MER-EUROPEAN VALUE-A1EUR | D13: Renta Variable | E13: Europa | F13: Value | G13: Europa | H13: EUR | I13: RV Europa value | J13: Revisar con folleto/BD definitiva | K13: Sí | L13: 44316 | M13: 46142 | N13: 61
... A63: 62 | B63: LU0200680600 Equity | C63: BGF-EMR MRK BD-A2 USD | D63: Renta Fija | E63: Deuda emergente | F63: Emerging market bonds | G63: Emergentes | H63: USD | I63: RF emergente | J63: Revisar con folleto/BD definitiva | K63: Sí | L63: 44316 | M63: 46142 | N63: 61

Sheet Resumen categorías
A1: Resumen de clasificación del universo de fondos
A3: Categoría principal | B3: Nº fondos | D3: Región | E3: Nº fondos
A4: Renta Variable | B4: 38 | D4: Global | E4: 25
A5: Renta Fija | B5: 20 | D5: Europa | E5: 11
A6: Materias Primas | B6: 2 | D6: EE.UU. | E6: 6
A7: Mixtos / Alternativos | B7: 2 | D7: Eurozona | E7: 6
D8: China | E8: 2
D9: Emergentes | E9: 2
D10: Europa/Global | E10: 2
D11: USD | E11: 2
D12: Asia | E12: 1
D13: Asia EM | E13: 1
D14: España | E14: 1
A15: Subcategoría | B15: Nº fondos | D15: Iberia | E15: 1
A16: Europa | B16: 5 | D16: India | E16: 1
A17: Global | B17: 5 | D17: Japón | E17: 1
A18: Estados Unidos | B18: 3
A19: Flexible global | B19: 3
A20: España / Iberia | B20: 2
A21: Global desarrollada | B21: 2
A22: Gobierno euro | B22: 2
A23: Gobierno euro inflación | B23: 2
A24: Liquidez euro | B24: 2
A25: Retorno absoluto / flexible | B25: 2
A26: Sectorial energía | B26: 2
A27: Sectorial tecnología | B27: 2
A28: Asia ex Japón | B28: 1
A29: Baja duración euro | B29: 1
... A57: Temática consumo/luxury | B57: 1

Sheet Notas app
A1: Uso propuesto de la base de datos en la app
A2: 1 | B2: Hoja original | C2: Mantener los precios históricos por fondo. Las fechas se usarán internamente, pero quedarán ocultas al alumno.
A3: 2 | B3: Clasificación fondos | C3: Tabla maestra para mostrar al alumno nombre, categoría, subcategoría y uso docente.
A4: 3 | B4: Categoría principal | C4: Permite filtrar por Renta Variable, Renta Fija, Materias Primas y Mixtos/Alternativos.
A5: 4 | B5: Subcategoría | C5: Permite imponer límites de cartera por bloque: RV USA, RV Europa, RF HY, liquidez, oro, etc.
A6: 5 | B6: Siguiente paso | C6: Conectar esta tabla al Streamlit y decidir qué campos verá el alumno y qué campos solo verá el profesor.
A8: Histórico incorporado | B8: Hoja 'Histórico liquidativos' | C8: Incluye fechas internas y PX_LAST por fondo.
A9: Rentabilidades | B9: Hoja 'Rentabilidades' | C9: Calculadas como variación mensual de los liquidativos.
A10: Control | B10: Hoja 'Cobertura histórico' | C10: Los 62 fondos tienen histórico asociado (61 observaciones).
A11: Uso en app | B11: Fechas ocultas | C11: La app usará la fecha internamente, pero mostrará Periodo 1, Periodo 2, etc.
A12: Observación | B12: MVP | C12: La clasificación sigue pendiente de validación final por folleto/base definitiva.

Sheet Histórico liquidativos
A1: Ticker Bloomberg | B1: IE00BYX5NX33 Equity | C1: LU1347437789 Equity | D1: LU1295551144 Equity | E1: LU1076253134 Equity | F1: LU0203975437 Equity | G1: ES0112611001 Equity | H1: IE00BD0NCM55 Equity | I1: ES0110485010 Equity | J1: IE00BDRK7L36 Equity | K1: LU0515381530 Equity | L1: IE00B8BPMF80 Equity | M1: LU0125951151 Equity | N1: ES0182769002 Equity | O1: FR0010288308 Equity | P1: LU1330191542 Equity | Q1: LU1598719752 Equity | R1: LU0861897477 Equity | S1: ES0119184002. Equity | T1: IE00BYX5N110 Equity | U1: IE00BYX5MX67 Equity | V1: LU0248185190 Equity | W1: LU0329070915 Equity | X1: IE00BJ5JPG56 Equity | Y1: LU2191242283 Equity | Z1: IE00BMWBB563 Equity | AA1: LU0248172537 Equity | AB1: IE0031786696 Equity | AC1: IE00B5648R31 Equity | AD1: LU1213836080 Equity | AE1: IE00B4468526 Equity | AF1: ES0165265002 Equity | AG1: LU2286300988 Equity | AH1: LU0171301533 Equity | AI1: JE00B78CGV99 Equity | AJ1: IE00BYTRR863 Equity | AK1: IE00BYTRR970 Equity | AL1: LU0329429897 Equity | AM1: DE000A0Q4R02 Equity | AN1: FR0011170182 Equity | AO1: JE00B1VS3770 Equity | AP1: LU0172157280 Equity | AQ1: LU0908524852 Equity | AR1: LU0599946893 Equity | AS1: LU1075212677 Equity | AT1: LU1361553693 Equity | AU1: LU1133289592 Equity | AV1: IE0007471471 Equity | AW1: LU0842209909 Equity | AX1: LU0290355717 Equity | AY1: FI0008804463 Equity | AZ1: FR0000978371 Equity | BA1: IE00BD0NC144 Equity | BB1: IE00B84J9L26 Equity | BC1: IE0033116579 Equity | BD1: LU0210246277 Equity | BE1: LU1694212348 Equity | BF1: LU0034353002 Equity | BG1: IE00BYW7LS16 Equity | BH1: LU0658026603 Equity | BI1: LU1319655087 Equity | BJ1: IE00B8J38129 Equity | BK1: LU0200680600 Equity
A2: Nombre fondo | B2: FIDELITY-MSCI WLD IDX-PAEUR | C2: NSF-WEALTH DEFEN GL EQ-A EUR | D2: CAPITAL GP NEW PERS-BEUR | E2: WELL GBL QTY GROWTH S EUR AC | F2: ROBECO BP GLBL PREM EQT-DEUR | G2: AZVALOR INTERNACIONAL FI | H2: ISHR DEV WRLD IDX-D ACC EUR | I2: TRESSIS CARTERA ECO30 FI-R | J2: ISHARE-EU-IF-EUR-DA | K2: CT LUX EUROPEAN G&I AINCEUR | L2: WELL STRAT EUR EQ-D EUR AC | M2: MFS MER-EUROPEAN VALUE-A1EUR | N2: VALENTUM FI-E | O2: GROUPAMA AVENIR EURO-NC | P2: MAGALLANES VALUE EUROPN EQ-R | Q2: COB LX SIC-COB INTERNA-PAEUR | R2: ABANTE GL-SPANISH OPP-B | S2: COBAS IBERIA FI | T2: FIDELITY S&P500 INDX PA EURH | U2: FIDELITY S&P500 INDX PA EUR | V2: SCHRODER INTL US LARG CP AE | W2: JUPITER JGF-INDIA SEL-L EUR | X2: ISHARES MSCI CHINA USD ACC | Y2: SCHRODER INTSEL CHN A-C EUR | Z2: MAN ASIA EX JAPAN EQUT-IFEUR | AA2: SCHRODER INT EME ASIA-A EUR | AB2: VANGUARD-EMR MK ST IN-EUR AC | AC2: MFP-MN JPN CRALP EQ-DEURHDGA | AD2: FIDELITY FNDS-GL TECH FD-A | AE2: POLAR CAPITAL-GLB TECH-RE | AF2: MYINV NASDAQ 100 FI- EUR | AG2: ALLIANZ CYBER SECURITY-ATEUR | AH2: BGF-WORLD ENERGY-A2 EUR | AI2: WT BRENT CRUDE OIL | AJ2: SS SPDR MS WRLD ENRG UCT ETF | AK2: SS SPDR MSCI WORLD FINA UC-U | AL2: GAM LUXURY BRANDS EQ-EUR B | AM2: ISHARES EUR 600 UTILITIES DE | AN2: OFI INVST PRECIOUS METALS-R | AO2: WISDOMTREE PHYSICAL GOLD | AP2: BGF-WORLD MINING FUND-EUR A2 | AQ2: HALLEY SICAV-ALINEA GLB-B | AR2: DWS CONCEPT KALDEMORGEN-LC | AS2: INVESCO PAN EUR HI IN-AQDGIE | AT2: PICTET-USD SHORT MT BDS-PEUR | AU2: SCHRODER INTL USD LIQ-A EUR | AV2: VANGUARD-US GOV BD IX-EUR HA | AW2: BLUEBAY INV GR EURO GV-CEUR | AX2: X EUROZONE GOVT BOND 1C | AY2: EVLI EURO LIKVIDI-B | AZ2: AXA IM EURO LIQUIDITY SRI-C | BA2: ISHARE-EU-GIL-BIF-D-EUR-A | BB2: PIMCO GIS-INCOME FUND-EEHA | BC2: NEWCAPITAL GVC-EUROA | BD2: ROBECO EURO CRDT BND-IE | BE2: NORDEA1 LOW DUR EUR C-BP EUR | BF2: DWS FLOATING RATE NOTES | BG2: GAM STAR INCOME-R ER HED ACC | BH2: AXA IM FIIS-EUR SH DUR H-F | BI2: AXA WF-US SH DUR H/Y BD-ACEH | BJ2: ALGEBRIS FINAN CR-R EUR | BK2: BGF-EMR MRK BD-A2 USD
A3: Campo | B3: PX_LAST | C3: PX_LAST | D3: PX_LAST | E3: PX_LAST | F3: PX_LAST | G3: PX_LAST | H3: PX_LAST | I3: PX_LAST | J3: PX_LAST | K3: PX_LAST | L3: PX_LAST | M3: PX_LAST | N3: PX_LAST | O3: PX_LAST | P3: PX_LAST | Q3: PX_LAST | R3: PX_LAST | S3: PX_LAST | T3: PX_LAST | U3: PX_LAST | V3: PX_LAST | W3: PX_LAST | X3: PX_LAST | Y3: PX_LAST | Z3: PX_LAST | AA3: PX_LAST | AB3: PX_LAST | AC3: PX_LAST | AD3: PX_LAST | AE3: PX_LAST | AF3: PX_LAST | AG3: PX_LAST | AH3: PX_LAST | AI3: PX_LAST | AJ3: PX_LAST | AK3: PX_LAST | AL3: PX_LAST | AM3: PX_LAST | AN3: PX_LAST | AO3: PX_LAST | AP3: PX_LAST | AQ3: PX_LAST | AR3: PX_LAST | AS3: PX_LAST | AT3: PX_LAST | AU3: PX_LAST | AV3: PX_LAST | AW3: PX_LAST | AX3: PX_LAST | AY3: PX_LAST | AZ3: PX_LAST | BA3: PX_LAST | BB3: PX_LAST | BC3: PX_LAST | BD3: PX_LAST | BE3: PX_LAST | BF3: PX_LAST | BG3: PX_LAST | BH3: PX_LAST | BI3: PX_LAST | BJ3: PX_LAST | BK3: PX_LAST
A4: Fecha | B4: Liquidativo / PX_LAST | C4: Liquidativo / PX_LAST | D4: Liquidativo / PX_LAST | E4: Liquidativo / PX_LAST | F4: Liquidativo / PX_LAST | G4: Liquidativo / PX_LAST | H4: Liquidativo / PX_LAST | I4: Liquidativo / PX_LAST | J4: Liquidativo / PX_LAST | K4: Liquidativo / PX_LAST | L4: Liquidativo / PX_LAST | M4: Liquidativo / PX_LAST | N4: Liquidativo / PX_LAST | O4: Liquidativo / PX_LAST | P4: Liquidativo / PX_LAST | Q4: Liquidativo / PX_LAST | R4: Liquidativo / PX_LAST | S4: Liquidativo / PX_LAST | T4: Liquidativo / PX_LAST | U4: Liquidativo / PX_LAST | V4: Liquidativo / PX_LAST | W4: Liquidativo / PX_LAST | X4: Liquidativo / PX_LAST | Y4: Liquidativo / PX_LAST | Z4: Liquidativo / PX_LAST | AA4: Liquidativo / PX_LAST | AB4: Liquidativo / PX_LAST | AC4: Liquidativo / PX_LAST | AD4: Liquidativo / PX_LAST | AE4: Liquidativo / PX_LAST | AF4: Liquidativo / PX_LAST | AG4: Liquidativo / PX_LAST | AH4: Liquidativo / PX_LAST | AI4: Liquidativo / PX_LAST | AJ4: Liquidativo / PX_LAST | AK4: Liquidativo / PX_LAST | AL4: Liquidativo / PX_LAST | AM4: Liquidativo / PX_LAST | AN4: Liquidativo / PX_LAST | AO4: Liquidativo / PX_LAST | AP4: Liquidativo / PX_LAST | AQ4: Liquidativo / PX_LAST | AR4: Liquidativo / PX_LAST | AS4: Liquidativo / PX_LAST | AT4: Liquidativo / PX_LAST | AU4: Liquidativo / PX_LAST | AV4: Liquidativo / PX_LAST | AW4: Liquidativo / PX_LAST | AX4: Liquidativo / PX_LAST | AY4: Liquidativo / PX_LAST | AZ4: Liquidativo / PX_LAST | BA4: Liquidativo / PX_LAST | BB4: Liquidativo / PX_LAST | BC4: Liquidativo / PX_LAST | BD4: Liquidativo / PX_LAST | BE4: Liquidativo / PX_LAST | BF4: Liquidativo / PX_LAST | BG4: Liquidativo / PX_LAST | BH4: Liquidativo / PX_LAST | BI4: Liquidativo / PX_LAST | BJ4: Liquidativo / PX_LAST | BK4: Liquidativo / PX_LAST
A5: 44316 | B5: 7.4964 | C5: 1419.88 | D5: 17.7 | E5: 29.8411 | F5: 324.91 | G5: 122.63777 | H5: 15.08 | I5: 117.98577 | J5: 12.3 | K5: 21.39 | L5: 21.6545 | M5: 56.03 | N5: 25.199092 | O5: 2268.19 | P5: 146.13187 | Q5: 73.14 | R5: 11.31 | S5: 95.072114 | T5: 7.3932 | U5: 8.1441 | V5: 195.6738 | W5: 15.81 | X5: 6.989 | Y5: 123.5518 | Z5: 109.84 | AA5: 50.8599 | AB5: 208.8901 | AC5: 168.09 | AD5: 33.05 | AE5: 70.91 | AF5: 1.0120381 | AG5: 95.85 | AH5: 11.78 | AI5: 27.54 | AJ5: 28.35 | AK5: 44.9925 | AL5: 403.01 | AM5: 38.125 | AN5: 928.51 | AO5: 168.1923 | AP5: 53.24 | AQ5: 74.85 | AR5: 157.57 | AS5: 9.79 | AT5: 117.1 | AU5: 107.5144 | AV5: 100.6391 | AW5: 117.27 | AX5: 248.78 | AY5: 25.42 | AZ5: 44471.005 | BA5: 11.18 | BB5: 13.83 | BC5: 177.35 | BD5: 165.6 | BE5: 102.52 | BF5: 83.79 | BG5: 10.1583 | BH5: 133.67 | BI5: 105.26 | BJ5: 166.97 | BK5: 19.92
A6: 44347 | B6: 7.4861 | C6: 1408.51 | D6: 17.62 | E6: 29.5164 | F6: 333.86 | G6: 136.63924 | H6: 15.13 | I6: 121.37115 | J6: 12.7 | K6: 21.55 | L6: 22.2254 | M6: 57.53 | N6: 25.663612 | O6: 2288.25 | P6: 151.65976 | Q6: 78.27 | R6: 11.58 | S6: 97.839096 | T6: 7.4357 | U6: 8.0706 | V6: 196.8774 | W6: 17.37 | X6: 6.989 | Y6: 128.4183 | Z6: 108.32 | AA6: 51.2079 | AB6: 210.3045 | AC6: 178.39 | AD6: 32.58 | AE6: 68.73 | AF6: 1.0120381 | AG6: 95.04 | AH6: 12.18 | AI6: 28.77 | AJ6: 28.9355 | AK6: 44.9925 | AL6: 415.32 | AM6: 38.53 | AN6: 955.85 | AO6: 178.7 | AP6: 55.26 | AQ6: 75.27 | AR6: 158.18 | AS6: 9.86 | AT6: 115.86 | AU6: 106.4813 | AV6: 100.9132 | AW6: 116.92 | AX6: 248.58 | AY6: 25.437 | AZ6: 44450.673 | BA6: 11.25 | BB6: 13.88 | BC6: 178.03 | BD6: 165.35 | BE6: 102.62 | BF6: 83.79 | BG6: 10.1635 | BH6: 133.91 | BI6: 105.38 | BJ6: 167.12 | BK6: 20.23
A7: 44377 | B7: 7.8348 | C7: 1489.06 | D7: 18.45 | E7: 30.7933 | F7: 334.68 | G7: 137.18066 | H7: 15.75 | I7: 121.48568 | J7: 12.85 | K7: 21.85 | L7: 22.5537 | M7: 58.24 | N7: 26.018181 | O7: 2390.22 | P7: 150.92619 | Q7: 77.95 | R7: 11.04 | S7: 95.002236 | T7: 7.6014 | U7: 8.5115 | V7: 205.5075 | W7: 18.02 | X7: 7.3717 | Y7: 129.276 | Z7: 109.36 | AA7: 51.2925 | AB7: 217.2312 | AC7: 175.58 | AD7: 34.39 | AE7: 74.75 | AF7: 1.0120381 | AG7: 105.28 | AH7: 12.9 | AI7: 30.995 | AJ7: 28.9355 | AK7: 53 | AL7: 431.15 | AM7: 37.89 | AN7: 892.45 | AO7: 175.65 | AP7: 53.23 | AQ7: 73.4 | AR7: 159.01 | AS7: 9.81 | AT7: 118.85 | AU7: 109.3027 | AV7: 101.4913 | AW7: 117.31 | AX7: 249.78 | AY7: 25.445 | AZ7: 44431.91 | BA7: 11.29 | BB7: 13.92 | BC7: 179.04 | BD7: 165.95 | BE7: 102.45 | BF7: 83.78 | BG7: 10.1852 | BH7: 134.18 | BI7: 105.87 | BJ7: 167.69 | BK7: 20.25
A8: 44407 | B8: 7.9702 | C8: 1521.78 | D8: 18.65 | E8: 31.5989 | F8: 333.48 | G8: 132.29831 | H8: 16.04 | I8: 121.22184 | J8: 13.09 | K8: 22.5 | L8: 23.3396 | M8: 59.78 | N8: 26.603345 | O8: 2572.85 | P8: 149.29012 | Q8: 73.67 | R8: 10.99 | S8: 92.204862 | T8: 7.7746 | U8: 8.7123 | V8: 209.2717 | W8: 18.81 | X8: 6.49 | Y8: 121.2812 | Z8: 103.42 | AA8: 49.6728 | AB8: 202.5746 | AC8: 172.61 | AD8: 34.37 | AE8: 75.14 | AF8: 1.035169 | AG8: 108.25 | AH8: 12 | AI8: 31.6 | AJ8: 29.35 | AK8: 51.6 | AL8: 441.37 | AM8: 38.225 | AN8: 881.43 | AO8: 169.85 | AP8: 55.52 | AQ8: 70.59 | AR8: 159.69 | AS8: 9.83 | AT8: 119.03 | AU8: 109.3091 | AV8: 102.7659 | AW8: 118.52 | AX8: 254.42 | AY8: 25.478 | AZ8: 44412.795 | BA8: 11.61 | BB8: 13.95 | BC8: 179.24 | BD8: 167.75 | BE8: 102.52 | BF8: 83.76 | BG8: 10.2024 | BH8: 134.35 | BI8: 105.84 | BJ8: 167.93 | BK8: 20.17
A9: 44439 | B9: 8.2043 | C9: 1550.43 | D9: 19.34 | E9: 32.7934 | F9: 339.53 | G9: 131.6918 | H9: 16.51 | I9: 122.60064 | J9: 13.35 | K9: 23.07 | L9: 23.7085 | M9: 61.44 | N9: 27.166419 | O9: 2693.09 | P9: 149.93172 | Q9: 76.56 | R9: 10.99 | S9: 94.814642 | T9: 7.9994 | U9: 9.0114 | V9: 214.8833 | W9: 19.74 | X9: 6.055 | Y9: 122.0114 | Z9: 107.43 | AA9: 49.4685 | AB9: 208.6034 | AC9: 174.68 | AD9: 35.53 | AE9: 78.04 | AF9: 1.075758 | AG9: 116.79 | AH9: 11.92 | AI9: 30.58 | AJ9: 27.68 | AK9: 54.25 | AL9: 426.46 | AM9: 39.87 | AN9: 848.94 | AO9: 170.73 | AP9: 52.33 | AQ9: 71.66 | AR9: 161.53 | AS9: 9.9 | AT9: 119.52 | AU9: 109.6781 | AV9: 102.5225 | AW9: 118.21 | AX9: 252.82 | AY9: 25.493 | AZ9: 44391.197 | BA9: 11.58 | BB9: 13.98 | BC9: 179.64 | BD9: 167.13 | BE9: 102.44 | BF9: 83.74 | BG9: 10.2207 | BH9: 134.56 | BI9: 106.06 | BJ9: 167.69 | BK9: 20.37
A10: 44469 | B10: 8.0138 | C10: 1493.37 | D10: 18.86 | E10: 31.6809 | F10: 336.17 | G10: 141.04284 | H10: 16.12 | I10: 122.70082 | J10: 12.95 | K10: 22.3 | L10: 23.0265 | M10: 58.85 | N10: 26.125585 | O10: 2530.53 | P10: 153.21045 | Q10: 81.01 | R10: 10.94 | S10: 95.146707 | T10: 7.614 | U10: 8.7488 | V10: 214.7066 | W10: 20.56 | X10: 6.055 | Y10: 121.1672 | Z10: 105.32 | AA10: 48.4443 | AB10: 203.099 | AC10: 183.93 | AD10: 34.84 | AE10: 74.64 | AF10: 1.0154807 | AG10: 112.78 | AH10: 13.56 | AI10: 33.59 | AJ10: 28.28 | AK10: 53.5432 | AL10: 412.39 | AM10: 36.39 | AN10: 770.34 | AO10: 165.54 | AP10: 48.17 | AQ10: 73.58 | AR10: 160.33 | AS10: 9.76 | AT10: 121.6 | AU10: 111.9962 | AV10: 101.3336 | AW10: 117.47 | AX10: 249.96 | AY10: 25.483 | AZ10: 44371.59 | BA10: 11.62 | BB10: 13.94 | BC10: 178.05 | BD10: 166.06 | BE10: 102.67 | BF10: 83.72 | BG10: 10.2457 | BH10: 134.48 | BI10: 106 | BJ10: 167.38 | BK10: 20.05
A11: 44498 | B11: 8.4747 | C11: 1567.07 | D11: 20.18 | E11: 33.4129 | F11: 346.4 | G11: 148.79664 | H11: 17.06 | I11: 124.19642 | J11: 13.56 | K11: 23.33 | L11: 23.7296 | M11: 62.3 | N11: 26.738703 | O11: 2682.96 | P11: 156.76894 | Q11: 82.18 | R11: 11.05 | S11: 98.059133 | T11: 8.1455 | U11: 9.3725 | V11: 222.6927 | W11: 20.52 | X11: 6.055 | Y11: 123.3728 | Z11: 109.96 | AA11: 50.4635 | AB11: 206.2279 | AC11: 180.66 | AD11: 36.09 | AE11: 78.67 | AF11: 1.0885212 | AG11: 122.43 | AH11: 14.8 | AI11: 36.03 | AJ11: 28.28 | AK11: 53.5432 | AL11: 441.68 | AM11: 38.775 | AN11: 804.42 | AO11: 170.71 | AP11: 51.37 | AQ11: 72.93 | AR11: 161.05 | AS11: 9.77 | AT11: 121.39 | AU11: 111.6311 | AV11: 101.1814 | AW11: 116.11 | AX11: 248.34 | AY11: 25.486 | AZ11: 44350.83 | BA11: 11.62 | BB11: 13.88 | BC11: 176.58 | BD11: 164.88 | BE11: 102.28 | BF11: 83.68 | BG11: 10.2952 | BH11: 134.11 | BI11: 105.89 | BJ11: 167.61 | BK11: 19.86
A12: 44530 | B12: 8.5226 | C12: 1562.96 | D12: 20.04 | E12: 33.6055 | F12: 339.65 | G12: 141.35263 | H12: 17.15 | I12: 120.74994 | J12: 13.23 | K12: 22.79 | L12: 22.8926 | M12: 60.84 | N12: 26.276238 | O12: 2717.5 | P12: 146.11928 | Q12: 77.63 | R12: 9.87 | S12: 93.474788 | T12: 8.0841 | U12: 9.5652 | V12: 225.9093 | W12: 20.57 | X12: 6.055 | Y12: 131.0768 | Z12: 109.51 | AA12: 49.8654 | AB12: 202.6239 | AC12: 169.01 | AD12: 36.23 | AE12: 81.57 | AF12: 1.118681 | AG12: 125.53 | AH12: 14.18 | AI12: 31.025 | AJ12: 28.28 | AK12: 53.45 | AL12: 467.49 | AM12: 38.315 | AN12: 753.85 | AO12: 167 | AP12: 51.74 | AQ12: 69.72 | AR12: 160.65 | AS12: 9.66 | AT12: 124.55 | AU12: 114.148 | AV12: 101.8994 | AW12: 117.35 | AX12: 252.08 | AY12: 25.475 | AZ12: 44326.812 | BA12: 11.8 | BB12: 13.74 | BC12: 174.99 | BD12: 165.52 | BE12: 101.55 | BF12: 83.59 | BG12: 10.2913 | BH12: 133.88 | BI12: 105.19 | BJ12: 165.89 | BK12: 19.27
A13: 44561 | B13: 8.7954 | C13: 1615.29 | D13: 20.36 | E13: 34.3179 | F13: 358.39 | G13: 146.34183 | H13: 17.8 | I13: 129.24402 | J13: 13.98 | K13: 23.74 | L13: 24.2584 | M13: 64.07 | N13: 26.909047 | O13: 2716.2 | P13: 152.847 | Q13: 79.54 | R13: 10.52 | S13: 95.645405 | T13: 8.4296 | U13: 9.888 | V13: 232.6209 | W13: 21.38 | X13: 5.6553 | Y13: 133.7636 | Z13: 109.28 | AA13: 50.3154 | AB13: 205.0677 | AC13: 176.08 | AD13: 37.38 | AE13: 80.1 | AF13: 1.1366477 | AG13: 122.43 | AH13: 14.59 | AI13: 34.39 | AJ13: 28.28 | AK13: 54.45 | AL13: 471.41 | AM13: 40.685 | AN13: 791.37 | AO13: 168 | AP13: 55.42 | AQ13: 72.79 | AR13: 163.68 | AS13: 9.73 | AT13: 123.08 | AU13: 114.2765 | AV13: 101.138 | AW13: 116.02 | AX13: 249.28 | AY13: 25.48 | AZ13: 44308.535 | BA13: 11.81 | BB13: 13.88 | BC13: 175.55 | BD13: 164.94 | BE13: 101.52 | BF13: 83.55 | BG13: 10.2983 | BH13: 134.68 | BI13: 106.2 | BJ13: 167.65 | BK13: 19.61
A14: 44592 | B14: 8.4508 | C14: 1580.95 | D14: 18.95 | E14: 31.782 | F14: 360.62 | G14: 153.8679 | H14: 17.01 | I14: 129.2796 | J14: 13.51 | K14: 22.63 | L14: 23.768 | M14: 61.02 | N14: 25.857194 | O14: 2299.63 | P14: 155.25796 | Q14: 81.56 | R14: 10.97 | S14: 96.958045 | T14: 7.9836 | U14: 9.5089 | V14: 225.0183 | W14: 21.5 | X14: 5.6553 | Y14: 120.2689 | Z14: 108.48 | AA14: 49.0274 | AB14: 204.1979 | AC14: 185.08 | AD14: 35.84 | AE14: 72.09 | AF14: 1.0151393 | AG14: 102.27 | AH14: 16.87 | AI14: 39.33 | AJ14: 28.28 | AK14: 58.1 | AL14: 428.45 | AM14: 39.92 | AN14: 820.91 | AO14: 173.62 | AP14: 55.39 | AQ14: 74.87 | AR14: 163.51 | AS14: 9.6 | AT14: 124.01 | AU14: 115.8417 | AV14: 99.2539 | AW14: 115.28 | AX14: 245.46 | AY14: 25.475 | AZ14: 44284.687 | BA14: 11.77 | BB14: 13.71 | BC14: 171.83 | BD14: 162.99 | BE14: 101.31 | BF14: 83.49 | BG14: 10.3059 | BH14: 133.48 | BI14: 105.02 | BJ14: 164.41 | BK14: 19.06
A15: 44620 | B15: 8.2209 | C15: 1485.22 | D15: 18.1 | E15: 30.5304 | F15: 360.48 | G15: 172.01192 | H15: 16.54 | I15: 130.38633 | J15: 13.1 | K15: 21.98 | L15: 23.1514 | M15: 58.71 | N15: 24.669201 | O15: 2176.52 | P15: 154.69192 | Q15: 83.37 | R15: 10.93 | S15: 96.803837 | T15: 7.7414 | U15: 9.2023 | V15: 218.981 | W15: 19.67 | X15: 5.4652 | Y15: 120.9245 | Z15: 104.75 | AA15: 47.8403 | AB15: 196.2867 | AC15: 186.45 | AD15: 34.67 | AE15: 69.71 | AF15: 0.9792744 | AG15: 102.82 | AH15: 17.45 | AI15: 43.8 | AJ15: 37.7211 | AK15: 55.3 | AL15: 407.54 | AM15: 39.87 | AN15: 867.09 | AO15: 178.9995 | AP15: 62.52 | AQ15: 74.58 | AR15: 160.9 | AS15: 9.33 | AT15: 123.37 | AU15: 115.5853 | AV15: 98.5421 | AW15: 112.94 | AX15: 241.3 | AY15: 25.42 | AZ15: 44254.338 | BA15: 11.75 | BB15: 13.33 | BC15: 167.26 | BD15: 158.98 | BE15: 100.81 | BF15: 83.31 | BG15: 10.3002 | BH15: 131.86 | BI15: 104.6 | BJ15: 160.52 | BK15: 17.91
A16: 44651 | B16: 8.5311 | C16: 1529.93 | D16: 18.85 | E16: 31.1066 | F16: 360.06 | G16: 191.38848 | H16: 17.16 | I16: 131.45944 | J16: 13.22 | K16: 22.37 | L16: 23.2862 | M16: 57.92 | N16: 24.429882 | O16: 2220.69 | P16: 159.03888 | Q16: 91.76 | R16: 10.99 | S16: 100.68319 | T16: 8.012 | U16: 9.6347 | V16: 232.3317 | W16: 20.52 | X16: 5.4652 | Y16: 108.2144 | Z16: 102.11 | AA16: 46.3212 | AB16: 194.8404 | AC16: 193.55 | AD16: 36.13 | AE16: 70.94 | AF16: 1.0167512 | AG16: 107.31 | AH16: 19.53 | AI16: 50.56 | AJ16: 41.1 | AK16: 54.17 | AL16: 404.69 | AM16: 39.04 | AN16: 856.04 | AO16: 186.6966 | AP16: 69.29 | AQ16: 76.96 | AR16: 162.85 | AS16: 9.26 | AT16: 123.11 | AU16: 116.6561 | AV16: 95.3346 | AW16: 110.69 | AX16: 235 | AY16: 25.394 | AZ16: 44222.633 | BA16: 12 | BB16: 13.17 | BC16: 165.05 | BD16: 157.04 | BE16: 101.18 | BF16: 83.12 | BG16: 10.2523 | BH16: 132.33 | BI16: 104.08 | BJ16: 160.62 | BK16: 18.36
... A65: 46142 | B65: 13.1168 | C65: 2055.8 | D65: 25.0373 | E65: 46.0964 | F65: 565.76 | G65: 356.52419 | H65: 26.41 | I65: 224.6228 | J65: 20.05 | K65: 32.92 | L65: 40.5005 | M65: 68.77 | N65: 31.481949 | O65: 1791.61 | P65: 257.48998 | Q65: 176.54 | R65: 24.81 | S65: 227.01619 | T65: 11.9256 | U65: 15.1469 | V65: 351.8502 | W65: 30.02 | X65: 5.8999 | Y65: 120.6162 | Z65: 162.11 | AA65: 66.0032 | AB65: 284.3181 | AC65: 501.61 | AD65: 62.6 | AE65: 204.87 | AF65: 1.545395 | AG65: 121.52 | AH65: 30.15 | AI65: 93.46 | AJ65: 72.577 | AK65: 93.6641 | AL65: 418.13 | AM65: 58.96 | AN65: 1481.39 | AO65: 423.3916 | AP65: 92.22 | AQ65: 106.95 | AR65: 186.12 | AS65: 8.51 | AT65: 132.73 | AU65: 129.6382 | AV65: 89.599 | AW65: 106.87 | AX65: 221.4 | AY65: 28.639 | AZ65: 49086.161 | BA65: 11.7 | BB65: 14.31 | BC65: 165.02 | BD65: 166.98 | BE65: 110.6078 | BF65: 93.5 | BG65: 11.2738 | BH65: 149.73 | BI65: 113.14 | BJ65: 190.99 | BK65: 23.73

Sheet Rentabilidades
A1: Ticker Bloomberg | B1: IE00BYX5NX33 Equity | C1: LU1347437789 Equity | D1: LU1295551144 Equity | E1: LU1076253134 Equity | F1: LU0203975437 Equity | G1: ES0112611001 Equity | H1: IE00BD0NCM55 Equity | I1: ES0110485010 Equity | J1: IE00BDRK7L36 Equity | K1: LU0515381530 Equity | L1: IE00B8BPMF80 Equity | M1: LU0125951151 Equity | N1: ES0182769002 Equity | O1: FR0010288308 Equity | P1: LU1330191542 Equity | Q1: LU1598719752 Equity | R1: LU0861897477 Equity | S1: ES0119184002. Equity | T1: IE00BYX5N110 Equity | U1: IE00BYX5MX67 Equity | V1: LU0248185190 Equity | W1: LU0329070915 Equity | X1: IE00BJ5JPG56 Equity | Y1: LU2191242283 Equity | Z1: IE00BMWBB563 Equity | AA1: LU0248172537 Equity | AB1: IE0031786696 Equity | AC1: IE00B5648R31 Equity | AD1: LU1213836080 Equity | AE1: IE00B4468526 Equity | AF1: ES0165265002 Equity | AG1: LU2286300988 Equity | AH1: LU0171301533 Equity | AI1: JE00B78CGV99 Equity | AJ1: IE00BYTRR863 Equity | AK1: IE00BYTRR970 Equity | AL1: LU0329429897 Equity | AM1: DE000A0Q4R02 Equity | AN1: FR0011170182 Equity | AO1: JE00B1VS3770 Equity | AP1: LU0172157280 Equity | AQ1: LU0908524852 Equity | AR1: LU0599946893 Equity | AS1: LU1075212677 Equity | AT1: LU1361553693 Equity | AU1: LU1133289592 Equity | AV1: IE0007471471 Equity | AW1: LU0842209909 Equity | AX1: LU0290355717 Equity | AY1: FI0008804463 Equity | AZ1: FR0000978371 Equity | BA1: IE00BD0NC144 Equity | BB1: IE00B84J9L26 Equity | BC1: IE0033116579 Equity | BD1: LU0210246277 Equity | BE1: LU1694212348 Equity | BF1: LU0034353002 Equity | BG1: IE00BYW7LS16 Equity | BH1: LU0658026603 Equity | BI1: LU1319655087 Equity | BJ1: IE00B8J38129 Equity | BK1: LU0200680600 Equity
A2: Nombre fondo | B2: FIDELITY-MSCI WLD IDX-PAEUR | C2: NSF-WEALTH DEFEN GL EQ-A EUR | D2: CAPITAL GP NEW PERS-BEUR | E2: WELL GBL QTY GROWTH S EUR AC | F2: ROBECO BP GLBL PREM EQT-DEUR | G2: AZVALOR INTERNACIONAL FI | H2: ISHR DEV WRLD IDX-D ACC EUR | I2: TRESSIS CARTERA ECO30 FI-R | J2: ISHARE-EU-IF-EUR-DA | K2: CT LUX EUROPEAN G&I AINCEUR | L2: WELL STRAT EUR EQ-D EUR AC | M2: MFS MER-EUROPEAN VALUE-A1EUR | N2: VALENTUM FI-E | O2: GROUPAMA AVENIR EURO-NC | P2: MAGALLANES VALUE EUROPN EQ-R | Q2: COB LX SIC-COB INTERNA-PAEUR | R2: ABANTE GL-SPANISH OPP-B | S2: COBAS IBERIA FI | T2: FIDELITY S&P500 INDX PA EURH | U2: FIDELITY S&P500 INDX PA EUR | V2: SCHRODER INTL US LARG CP AE | W2: JUPITER JGF-INDIA SEL-L EUR | X2: ISHARES MSCI CHINA USD ACC | Y2: SCHRODER INTSEL CHN A-C EUR | Z2: MAN ASIA EX JAPAN EQUT-IFEUR | AA2: SCHRODER INT EME ASIA-A EUR | AB2: VANGUARD-EMR MK ST IN-EUR AC | AC2: MFP-MN JPN CRALP EQ-DEURHDGA | AD2: FIDELITY FNDS-GL TECH FD-A | AE2: POLAR CAPITAL-GLB TECH-RE | AF2: MYINV NASDAQ 100 FI- EUR | AG2: ALLIANZ CYBER SECURITY-ATEUR | AH2: BGF-WORLD ENERGY-A2 EUR | AI2: WT BRENT CRUDE OIL | AJ2: SS SPDR MS WRLD ENRG UCT ETF | AK2: SS SPDR MSCI WORLD FINA UC-U | AL2: GAM LUXURY BRANDS EQ-EUR B | AM2: ISHARES EUR 600 UTILITIES DE | AN2: OFI INVST PRECIOUS METALS-R | AO2: WISDOMTREE PHYSICAL GOLD | AP2: BGF-WORLD MINING FUND-EUR A2 | AQ2: HALLEY SICAV-ALINEA GLB-B | AR2: DWS CONCEPT KALDEMORGEN-LC | AS2: INVESCO PAN EUR HI IN-AQDGIE | AT2: PICTET-USD SHORT MT BDS-PEUR | AU2: SCHRODER INTL USD LIQ-A EUR | AV2: VANGUARD-US GOV BD IX-EUR HA | AW2: BLUEBAY INV GR EURO GV-CEUR | AX2: X EUROZONE GOVT BOND 1C | AY2: EVLI EURO LIKVIDI-B | AZ2: AXA IM EURO LIQUIDITY SRI-C | BA2: ISHARE-EU-GIL-BIF-D-EUR-A | BB2: PIMCO GIS-INCOME FUND-EEHA | BC2: NEWCAPITAL GVC-EUROA | BD2: ROBECO EURO CRDT BND-IE | BE2: NORDEA1 LOW DUR EUR C-BP EUR | BF2: DWS FLOATING RATE NOTES | BG2: GAM STAR INCOME-R ER HED ACC | BH2: AXA IM FIIS-EUR SH DUR H-F | BI2: AXA WF-US SH DUR H/Y BD-ACEH | BJ2: ALGEBRIS FINAN CR-R EUR | BK2: BGF-EMR MRK BD-A2 USD
A3: Campo | B3: Rentabilidad mensual | C3: Rentabilidad mensual | D3: Rentabilidad mensual | E3: Rentabilidad mensual | F3: Rentabilidad mensual | G3: Rentabilidad mensual | H3: Rentabilidad mensual | I3: Rentabilidad mensual | J3: Rentabilidad mensual | K3: Rentabilidad mensual | L3: Rentabilidad mensual | M3: Rentabilidad mensual | N3: Rentabilidad mensual | O3: Rentabilidad mensual | P3: Rentabilidad mensual | Q3: Rentabilidad mensual | R3: Rentabilidad mensual | S3: Rentabilidad mensual | T3: Rentabilidad mensual | U3: Rentabilidad mensual | V3: Rentabilidad mensual | W3: Rentabilidad mensual | X3: Rentabilidad mensual | Y3: Rentabilidad mensual | Z3: Rentabilidad mensual | AA3: Rentabilidad mensual | AB3: Rentabilidad mensual | AC3: Rentabilidad mensual | AD3: Rentabilidad mensual | AE3: Rentabilidad mensual | AF3: Rentabilidad mensual | AG3: Rentabilidad mensual | AH3: Rentabilidad mensual | AI3: Rentabilidad mensual | AJ3: Rentabilidad mensual | AK3: Rentabilidad mensual | AL3: Rentabilidad mensual | AM3: Rentabilidad mensual | AN3: Rentabilidad mensual | AO3: Rentabilidad mensual | AP3: Rentabilidad mensual | AQ3: Rentabilidad mensual | AR3: Rentabilidad mensual | AS3: Rentabilidad mensual | AT3: Rentabilidad mensual | AU3: Rentabilidad mensual | AV3: Rentabilidad mensual | AW3: Rentabilidad mensual | AX3: Rentabilidad mensual | AY3: Rentabilidad mensual | AZ3: Rentabilidad mensual | BA3: Rentabilidad mensual | BB3: Rentabilidad mensual | BC3: Rentabilidad mensual | BD3: Rentabilidad mensual | BE3: Rentabilidad mensual | BF3: Rentabilidad mensual | BG3: Rentabilidad mensual | BH3: Rentabilidad mensual | BI3: Rentabilidad mensual | BJ3: Rentabilidad mensual | BK3: Rentabilidad mensual
A4: Fecha | B4: Retorno | C4: Retorno | D4: Retorno | E4: Retorno | F4: Retorno | G4: Retorno | H4: Retorno | I4: Retorno | J4: Retorno | K4: Retorno | L4: Retorno | M4: Retorno | N4: Retorno | O4: Retorno | P4: Retorno | Q4: Retorno | R4: Retorno | S4: Retorno | T4: Retorno | U4: Retorno | V4: Retorno | W4: Retorno | X4: Retorno | Y4: Retorno | Z4: Retorno | AA4: Retorno | AB4: Retorno | AC4: Retorno | AD4: Retorno | AE4: Retorno | AF4: Retorno | AG4: Retorno | AH4: Retorno | AI4: Retorno | AJ4: Retorno | AK4: Retorno | AL4: Retorno | AM4: Retorno | AN4: Retorno | AO4: Retorno | AP4: Retorno | AQ4: Retorno | AR4: Retorno | AS4: Retorno | AT4: Retorno | AU4: Retorno | AV4: Retorno | AW4: Retorno | AX4: Retorno | AY4: Retorno | AZ4: Retorno | BA4: Retorno | BB4: Retorno | BC4: Retorno | BD4: Retorno | BE4: Retorno | BF4: Retorno | BG4: Retorno | BH4: Retorno | BI4: Retorno | BJ4: Retorno | BK4: Retorno
A5: 44347 | B5: =IFERROR('Histórico liquidativos'!B6/'Histórico liquidativos'!B5-1,"") -> -0.0013739928 | C5: =IFERROR('Histórico liquidativos'!C6/'Histórico liquidativos'!C5-1,"") -> -0.008007719 | D5: =IFERROR('Histórico liquidativos'!D6/'Histórico liquidativos'!D5-1,"") -> -0.004519774 | E5: =IFERROR('Histórico liquidativos'!E6/'Histórico liquidativos'!E5-1,"") -> -0.010880966 | F5: =IFERROR('Histórico liquidativos'!F6/'Histórico liquidativos'!F5-1,"") -> 0.02754609 | G5: =IFERROR('Histórico liquidativos'!G6/'Histórico liquidativos'!G5-1,"") -> 0.11416925 | H5: =IFERROR('Histórico liquidativos'!H6/'Histórico liquidativos'!H5-1,"") -> 0.0033156499 | I5: =IFERROR('Histórico liquidativos'!I6/'Histórico liquidativos'!I5-1,"") -> 0.028693096 | ... BK5: =IFERROR('Histórico liquidativos'!BK6/'Histórico liquidativos'!BK5-1,"") -> 0.015562249
A6: 44377 | B6: =IFERROR('Histórico liquidativos'!B7/'Histórico liquidativos'!B6-1,"") -> 0.046579661 | C6: =IFERROR('Histórico liquidativos'!C7/'Histórico liquidativos'!C6-1,"") -> 0.057188092 | D6: =IFERROR('Histórico liquidativos'!D7/'Histórico liquidativos'!D6-1,"") -> 0.047105562 | E6: =IFERROR('Histórico liquidativos'!E7/'Histórico liquidativos'!E6-1,"") -> 0.043260696 | F6: =IFERROR('Histórico liquidativos'!F7/'Histórico liquidativos'!F6-1,"") -> 0.0024561193 | G6: =IFERROR('Histórico liquidativos'!G7/'Histórico liquidativos'!G6-1,"") -> 0.003962427 | H6: =IFERROR('Histórico liquidativos'!H7/'Histórico liquidativos'!H6-1,"") -> 0.040978189 | I6: =IFERROR('Histórico liquidativos'!I7/'Histórico liquidativos'!I6-1,"") -> 0.00094361799 | ... BK6: =IFERROR('Histórico liquidativos'!BK7/'Histórico liquidativos'!BK6-1,"") -> 0.00098863075
A7: 44407 | B7: =IFERROR('Histórico liquidativos'!B8/'Histórico liquidativos'!B7-1,"") -> 0.017281871 | C7: =IFERROR('Histórico liquidativos'!C8/'Histórico liquidativos'!C7-1,"") -> 0.021973594 | D7: =IFERROR('Histórico liquidativos'!D8/'Histórico liquidativos'!D7-1,"") -> 0.010840108 | E7: =IFERROR('Histórico liquidativos'!E8/'Histórico liquidativos'!E7-1,"") -> 0.026161535 | F7: =IFERROR('Histórico liquidativos'!F8/'Histórico liquidativos'!F7-1,"") -> -0.0035855145 | G7: =IFERROR('Histórico liquidativos'!G8/'Histórico liquidativos'!G7-1,"") -> -0.035590652 | H7: =IFERROR('Histórico liquidativos'!H8/'Histórico liquidativos'!H7-1,"") -> 0.018412698 | I7: =IFERROR('Histórico liquidativos'!I8/'Histórico liquidativos'!I7-1,"") -> -0.0021717161 | ... BK7: =IFERROR('Histórico liquidativos'!BK8/'Histórico liquidativos'!BK7-1,"") -> -0.0039506173
A8: 44439 | B8: =IFERROR('Histórico liquidativos'!B9/'Histórico liquidativos'!B8-1,"") -> 0.02937191 | C8: =IFERROR('Histórico liquidativos'!C9/'Histórico liquidativos'!C8-1,"") -> 0.018826637 | D8: =IFERROR('Histórico liquidativos'!D9/'Histórico liquidativos'!D8-1,"") -> 0.036997319 | E8: =IFERROR('Histórico liquidativos'!E9/'Histórico liquidativos'!E8-1,"") -> 0.037801949 | F8: =IFERROR('Histórico liquidativos'!F9/'Histórico liquidativos'!F8-1,"") -> 0.018142018 | G8: =IFERROR('Histórico liquidativos'!G9/'Histórico liquidativos'!G8-1,"") -> -0.0045844426 | H8: =IFERROR('Histórico liquidativos'!H9/'Histórico liquidativos'!H8-1,"") -> 0.029301746 | I8: =IFERROR('Histórico liquidativos'!I9/'Histórico liquidativos'!I8-1,"") -> 0.011374176 | ... BK8: =IFERROR('Histórico liquidativos'!BK9/'Histórico liquidativos'!BK8-1,"") -> 0.0099157164
A9: 44469 | B9: =IFERROR('Histórico liquidativos'!B10/'Histórico liquidativos'!B9-1,"") -> -0.023219531 | C9: =IFERROR('Histórico liquidativos'!C10/'Histórico liquidativos'!C9-1,"") -> -0.036802693 | D9: =IFERROR('Histórico liquidativos'!D10/'Histórico liquidativos'!D9-1,"") -> -0.024819028 | E9: =IFERROR('Histórico liquidativos'!E10/'Histórico liquidativos'!E9-1,"") -> -0.033924509 | F9: =IFERROR('Histórico liquidativos'!F10/'Histórico liquidativos'!F9-1,"") -> -0.0098960328 | G9: =IFERROR('Histórico liquidativos'!G10/'Histórico liquidativos'!G9-1,"") -> 0.071007051 | H9: =IFERROR('Histórico liquidativos'!H10/'Histórico liquidativos'!H9-1,"") -> -0.023622047 | I9: =IFERROR('Histórico liquidativos'!I10/'Histórico liquidativos'!I9-1,"") -> 0.00081708951 | ... BK9: =IFERROR('Histórico liquidativos'!BK10/'Histórico liquidativos'!BK9-1,"") -> -0.015709377
A10: 44498 | B10: =IFERROR('Histórico liquidativos'!B11/'Histórico liquidativos'!B10-1,"") -> 0.05751329 | C10: =IFERROR('Histórico liquidativos'!C11/'Histórico liquidativos'!C10-1,"") -> 0.049351467 | D10: =IFERROR('Histórico liquidativos'!D11/'Histórico liquidativos'!D10-1,"") -> 0.069989396 | E10: =IFERROR('Histórico liquidativos'!E11/'Histórico liquidativos'!E10-1,"") -> 0.054670164 | F10: =IFERROR('Histórico liquidativos'!F11/'Histórico liquidativos'!F10-1,"") -> 0.030431032 | G10: =IFERROR('Histórico liquidativos'!G11/'Histórico liquidativos'!G10-1,"") -> 0.054974765 | H10: =IFERROR('Histórico liquidativos'!H11/'Histórico liquidativos'!H10-1,"") -> 0.058312655 | I10: =IFERROR('Histórico liquidativos'!I11/'Histórico liquidativos'!I10-1,"") -> 0.01218903 | ... BK10: =IFERROR('Histórico liquidativos'!BK11/'Histórico liquidativos'!BK10-1,"") -> -0.0094763092
A11: 44530 | B11: =IFERROR('Histórico liquidativos'!B12/'Histórico liquidativos'!B11-1,"") -> 0.0056521175 | C11: =IFERROR('Histórico liquidativos'!C12/'Histórico liquidativos'!C11-1,"") -> -0.002622729 | D11: =IFERROR('Histórico liquidativos'!D12/'Histórico liquidativos'!D11-1,"") -> -0.0069375619 | E11: =IFERROR('Histórico liquidativos'!E12/'Histórico liquidativos'!E11-1,"") -> 0.0057642408 | F11: =IFERROR('Histórico liquidativos'!F12/'Histórico liquidativos'!F11-1,"") -> -0.019486143 | G11: =IFERROR('Histórico liquidativos'!G12/'Histórico liquidativos'!G11-1,"") -> -0.050028086 | H11: =IFERROR('Histórico liquidativos'!H12/'Histórico liquidativos'!H11-1,"") -> 0.0052754982 | I11: =IFERROR('Histórico liquidativos'!I12/'Histórico liquidativos'!I11-1,"") -> -0.027750268 | ... BK11: =IFERROR('Histórico liquidativos'!BK12/'Histórico liquidativos'!BK11-1,"") -> -0.029707956
A12: 44561 | B12: =IFERROR('Histórico liquidativos'!B13/'Histórico liquidativos'!B12-1,"") -> 0.032009011 | C12: =IFERROR('Histórico liquidativos'!C13/'Histórico liquidativos'!C12-1,"") -> 0.033481343 | D12: =IFERROR('Histórico liquidativos'!D13/'Histórico liquidativos'!D12-1,"") -> 0.015968064 | E12: =IFERROR('Histórico liquidativos'!E13/'Histórico liquidativos'!E12-1,"") -> 0.021198911 | F12: =IFERROR('Histórico liquidativos'!F13/'Histórico liquidativos'!F12-1,"") -> 0.055174444 | G12: =IFERROR('Histórico liquidativos'!G13/'Histórico liquidativos'!G12-1,"") -> 0.035296175 | H12: =IFERROR('Histórico liquidativos'!H13/'Histórico liquidativos'!H12-1,"") -> 0.037900875 | I12: =IFERROR('Histórico liquidativos'!I13/'Histórico liquidativos'!I12-1,"") -> 0.070344383 | ... BK12: =IFERROR('Histórico liquidativos'!BK13/'Histórico liquidativos'!BK12-1,"") -> 0.017644006
A13: 44592 | B13: =IFERROR('Histórico liquidativos'!B14/'Histórico liquidativos'!B13-1,"") -> -0.039179571 | C13: =IFERROR('Histórico liquidativos'!C14/'Histórico liquidativos'!C13-1,"") -> -0.02125934 | D13: =IFERROR('Histórico liquidativos'!D14/'Histórico liquidativos'!D13-1,"") -> -0.069253438 | E13: =IFERROR('Histórico liquidativos'!E14/'Histórico liquidativos'!E13-1,"") -> -0.073894382 | F13: =IFERROR('Histórico liquidativos'!F14/'Histórico liquidativos'!F13-1,"") -> 0.0062222718 | G13: =IFERROR('Histórico liquidativos'!G14/'Histórico liquidativos'!G13-1,"") -> 0.051428015 | H13: =IFERROR('Histórico liquidativos'!H14/'Histórico liquidativos'!H13-1,"") -> -0.044382022 | I13: =IFERROR('Histórico liquidativos'!I14/'Histórico liquidativos'!I13-1,"") -> 0.00027530094 | ... BK13: =IFERROR('Histórico liquidativos'!BK14/'Histórico liquidativos'!BK13-1,"") -> -0.028046915
A14: 44620 | B14: =IFERROR('Histórico liquidativos'!B15/'Histórico liquidativos'!B14-1,"") -> -0.027204525 | C14: =IFERROR('Histórico liquidativos'!C15/'Histórico liquidativos'!C14-1,"") -> -0.0605522 | D14: =IFERROR('Histórico liquidativos'!D15/'Histórico liquidativos'!D14-1,"") -> -0.044854881 | E14: =IFERROR('Histórico liquidativos'!E15/'Histórico liquidativos'!E14-1,"") -> -0.039380782 | F14: =IFERROR('Histórico liquidativos'!F15/'Histórico liquidativos'!F14-1,"") -> -0.00038822029 | G14: =IFERROR('Histórico liquidativos'!G15/'Histórico liquidativos'!G14-1,"") -> 0.11791945 | H14: =IFERROR('Histórico liquidativos'!H15/'Histórico liquidativos'!H14-1,"") -> -0.027630805 | I14: =IFERROR('Histórico liquidativos'!I15/'Histórico liquidativos'!I14-1,"") -> 0.0085607165 | ... BK14: =IFERROR('Histórico liquidativos'!BK15/'Histórico liquidativos'!BK14-1,"") -> -0.060335782
A15: 44651 | B15: =IFERROR('Histórico liquidativos'!B16/'Histórico liquidativos'!B15-1,"") -> 0.037733095 | C15: =IFERROR('Histórico liquidativos'!C16/'Histórico liquidativos'!C15-1,"") -> 0.030103284 | D15: =IFERROR('Histórico liquidativos'!D16/'Histórico liquidativos'!D15-1,"") -> 0.041436464 | E15: =IFERROR('Histórico liquidativos'!E16/'Histórico liquidativos'!E15-1,"") -> 0.018872992 | F15: =IFERROR('Histórico liquidativos'!F16/'Histórico liquidativos'!F15-1,"") -> -0.0011651132 | G15: =IFERROR('Histórico liquidativos'!G16/'Histórico liquidativos'!G15-1,"") -> 0.11264659 | H15: =IFERROR('Histórico liquidativos'!H16/'Histórico liquidativos'!H15-1,"") -> 0.037484885 | I15: =IFERROR('Histórico liquidativos'!I16/'Histórico liquidativos'!I15-1,"") -> 0.0082302726 | ... BK15: =IFERROR('Histórico liquidativos'!BK16/'Histórico liquidativos'!BK15-1,"") -> 0.025125628
A16: 44680 | B16: =IFERROR('Histórico liquidativos'!B17/'Histórico liquidativos'!B16-1,"") -> -0.032656984 | C16: =IFERROR('Histórico liquidativos'!C17/'Histórico liquidativos'!C16-1,"") -> -0.048381298 | D16: =IFERROR('Histórico liquidativos'!D17/'Histórico liquidativos'!D16-1,"") -> -0.058885942 | E16: =IFERROR('Histórico liquidativos'!E17/'Histórico liquidativos'!E16-1,"") -> -0.031925701 | F16: =IFERROR('Histórico liquidativos'!F17/'Histórico liquidativos'!F16-1,"") -> 0.0013608843 | G16: =IFERROR('Histórico liquidativos'!G17/'Histórico liquidativos'!G16-1,"") -> 0.062944024 | H16: =IFERROR('Histórico liquidativos'!H17/'Histórico liquidativos'!H16-1,"") -> -0.032634033 | I16: =IFERROR('Histórico liquidativos'!I17/'Histórico liquidativos'!I16-1,"") -> -0.0027938123 | ... BK16: =IFERROR('Histórico liquidativos'!BK17/'Histórico liquidativos'!BK16-1,"") -> -0.05664488
... A64: 46142 | B64: =IFERROR('Histórico liquidativos'!B65/'Histórico liquidativos'!B64-1,"") -> 0.076453402 | C64: =IFERROR('Histórico liquidativos'!C65/'Histórico liquidativos'!C64-1,"") -> 0.043669851 | D64: =IFERROR('Histórico liquidativos'!D65/'Histórico liquidativos'!D64-1,"") -> 0.062306948 | E64: =IFERROR('Histórico liquidativos'!E65/'Histórico liquidativos'!E64-1,"") -> 0.087943885 | F64: =IFERROR('Histórico liquidativos'!F65/'Histórico liquidativos'!F64-1,"") -> 0.035754169 | G64: =IFERROR('Histórico liquidativos'!G65/'Histórico liquidativos'!G64-1,"") -> 0.033456847 | H64: =IFERROR('Histórico liquidativos'!H65/'Histórico liquidativos'!H64-1,"") -> 0.076640848 | I64: =IFERROR('Histórico liquidativos'!I65/'Histórico liquidativos'!I64-1,"") -> 0.061710812 | ... BK64: =IFERROR('Histórico liquidativos'!BK65/'Histórico liquidativos'!BK64-1,"") -> 0.034437663

Sheet Cobertura histórico
A1: Ticker / ISIN Bloomberg | B1: Nombre fondo | C1: En clasificación | D1: En histórico | E1: Primera fecha | F1: Última fecha | G1: Nº observaciones | H1: Observaciones
A2: IE00BYX5NX33 Equity | B2: FIDELITY-MSCI WLD IDX-PAEUR | C2: Sí | D2: Sí | E2: 44316 | F2: 46142 | G2: 61 | H2: OK
A3: LU1347437789 Equity | B3: NSF-WEALTH DEFEN GL EQ-A EUR | C3: Sí | D3: Sí | E3: 44316 | F3: 46142 | G3: 61 | H3: OK
A4: LU1295551144 Equity | B4: CAPITAL GP NEW PERS-BEUR | C4: Sí | D4: Sí | E4: 44316 | F4: 46142 | G4: 61 | H4: OK
A5: LU1076253134 Equity | B5: WELL GBL QTY GROWTH S EUR AC | C5: Sí | D5: Sí | E5: 44316 | F5: 46142 | G5: 61 | H5: OK
A6: LU0203975437 Equity | B6: ROBECO BP GLBL PREM EQT-DEUR | C6: Sí | D6: Sí | E6: 44316 | F6: 46142 | G6: 61 | H6: OK
A7: ES0112611001 Equity | B7: AZVALOR INTERNACIONAL FI | C7: Sí | D7: Sí | E7: 44316 | F7: 46142 | G7: 61 | H7: OK
A8: IE00BD0NCM55 Equity | B8: ISHR DEV WRLD IDX-D ACC EUR | C8: Sí | D8: Sí | E8: 44316 | F8: 46142 | G8: 61 | H8: OK
A9: ES0110485010 Equity | B9: TRESSIS CARTERA ECO30 FI-R | C9: Sí | D9: Sí | E9: 44316 | F9: 46142 | G9: 61 | H9: OK
A10: IE00BDRK7L36 Equity | B10: ISHARE-EU-IF-EUR-DA | C10: Sí | D10: Sí | E10: 44316 | F10: 46142 | G10: 61 | H10: OK
A11: LU0515381530 Equity | B11: CT LUX EUROPEAN G&I AINCEUR | C11: Sí | D11: Sí | E11: 44316 | F11: 46142 | G11: 61 | H11: OK
A12: IE00B8BPMF80 Equity | B12: WELL STRAT EUR EQ-D EUR AC | C12: Sí | D12: Sí | E12: 44316 | F12: 46142 | G12: 61 | H12: OK
A13: LU0125951151 Equity | B13: MFS MER-EUROPEAN VALUE-A1EUR | C13: Sí | D13: Sí | E13: 44316 | F13: 46142 | G13: 61 | H13: OK
... A63: LU0200680600 Equity | B63: BGF-EMR MRK BD-A2 USD | C63: Sí | D63: Sí | E63: 44316 | F63: 46142 | G63: 61 | H63: OK
